weedi/__init__.py
weedi/config.py
weedi/exc.py
weedi/loadable.py
weedi/loadables_repository.py
weedi-1.0.dist-info/DESCRIPTION.rst
weedi-1.0.dist-info/METADATA
weedi-1.0.dist-info/RECORD
weedi-1.0.dist-info/WHEEL
weedi-1.0.dist-info/metadata.json
weedi-1.0.dist-info/top_level.txt
