Metadata-Version: 2.0
Name: weedi
Version: 1.0
Summary: A dependency injection system/container using setuptools entry points
Home-page: https://github.com/weenect/weedi
Author: UNKNOWN
Author-email: UNKNOWN
License: MIT
Download-URL: https://github.com/weenect/weedi/tarball/1.0
Keywords: di,dependency injection,entry points,entry_points,setuptools
Platform: UNKNOWN
Classifier: Development Status :: 5 - Production/Stable
Classifier: Intended Audience :: Developers
Classifier: License :: OSI Approved :: MIT License
Classifier: Programming Language :: Python :: 2.7
Classifier: Programming Language :: Python :: 3.3
Classifier: Programming Language :: Python :: 3.4
Classifier: Programming Language :: Python :: 3.5
Classifier: Topic :: Software Development :: Libraries :: Application Frameworks
Requires: configobj
Requires-Dist: configobj
Provides-Extra: test
Requires-Dist: mock; extra == 'test'
